rebo/__init__.py
rebo/cli.py
rebo/core.py
rebo/templates.py
rebo/commands/doctor.py
rebo/commands/index.py
rebo/commands/init.py
rebo/commands/jsondiff.py
rebo/commands/md2pdf.py
rebo_toolkit-0.1.0.dist-info/licenses/LICENSE
rebo_toolkit-0.1.0.dist-info/METADATA
rebo_toolkit-0.1.0.dist-info/WHEEL
rebo_toolkit-0.1.0.dist-info/entry_points.txt
rebo_toolkit-0.1.0.dist-info/top_level.txt
rebo_toolkit-0.1.0.dist-info/RECORD
