Metadata-Version: 2.4
Name: rebo-toolkit
Version: 0.1.0
Summary: Repo bootstrap + repo utilities (init/doctor/md2pdf/jsondiff/index).
Author: rebo contributors
License: MIT
Requires-Python: >=3.9
License-File: LICENSE
Requires-Dist: reportlab>=4.0.0
Provides-Extra: dev
Requires-Dist: pytest>=8; extra == "dev"
Dynamic: license-file
